setup.py
simpholib/Library.py
simpholib/Photo.py
simpholib/__init__.py
simpholib/action.py
simpholib/command_line.py
simpholib.egg-info/PKG-INFO
simpholib.egg-info/SOURCES.txt
simpholib.egg-info/dependency_links.txt
simpholib.egg-info/entry_points.txt
simpholib.egg-info/not-zip-safe
simpholib.egg-info/top_level.txt