Metadata-Version: 1.1
Name: simpholib
Version: 1.0b1
Summary: Simple Photo Library
Home-page: https://github.com/dstdnk/simple-photo-library
Author: Dmitry Stadnik
Author-email: dmitry.stadnik.mail@gmail.com
License: MIT
Download-URL: https://github.com/dstdnk/simple-photo-library/tarball/v1.0b1
Platform: UNKNOWN
